{
    "name": "perl",
    "total": 276,
    "compatible": 240,
    "incompatible": [
        {
            "pattern": "\\2",
            "error": "Compilation failed: reference to non-existent subpattern at offset 1"
        },
        {
            "pattern": "\\2",
            "error": "Compilation failed: reference to non-existent subpattern at offset 1"
        },
        {
            "pattern": "\\1",
            "error": "Compilation failed: reference to non-existent subpattern at offset 1"
        },
        {
            "pattern": "(?=\\2)",
            "error": "Compilation failed: reference to non-existent subpattern at offset 4"
        },
        {
            "pattern": "\\1",
            "error": "Compilation failed: reference to non-existent subpattern at offset 1"
        },
        {
            "pattern": "(?=\\2)",
            "error": "Compilation failed: reference to non-existent subpattern at offset 4"
        },
        {
            "pattern": "\\1(?=[acdegilmoprsu]*x[acdegilmoprsu]*)\\b",
            "error": "Compilation failed: reference to non-existent subpattern at offset 1"
        },
        {
            "pattern": "(?<=[\\&({|~]|if|unless|^)\\s*((/))",
            "error": "Unknown modifier ')'"
        },
        {
            "pattern": "\\$(?=/)",
            "error": "Unknown modifier ')'"
        },
        {
            "pattern": "\\1",
            "error": "Compilation failed: reference to non-existent subpattern at offset 1"
        },
        {
            "pattern": "\\1",
            "error": "Compilation failed: reference to non-existent subpattern at offset 1"
        },
        {
            "pattern": "\\1",
            "error": "Compilation failed: reference to non-existent subpattern at offset 1"
        },
        {
            "pattern": "^((?!\\5)\\s+)?((\\6))$",
            "error": "Compilation failed: reference to non-existent subpattern at offset 6"
        },
        {
            "pattern": "^((?!\\5)\\s+)?((\\6))$",
            "error": "Compilation failed: reference to non-existent subpattern at offset 6"
        },
        {
            "pattern": "^((?!\\5)\\s+)?((\\6))$",
            "error": "Compilation failed: reference to non-existent subpattern at offset 6"
        },
        {
            "pattern": "^((?!\\5)\\s+)?((\\6))$",
            "error": "Compilation failed: reference to non-existent subpattern at offset 6"
        },
        {
            "pattern": "^((?!\\5)\\s+)?((\\6))$",
            "error": "Compilation failed: reference to non-existent subpattern at offset 6"
        },
        {
            "pattern": "^((?!\\5)\\s+)?((\\6))$",
            "error": "Compilation failed: reference to non-existent subpattern at offset 6"
        },
        {
            "pattern": "^((?!\\5)\\s+)?((\\6))$",
            "error": "Compilation failed: reference to non-existent subpattern at offset 6"
        },
        {
            "pattern": "^((?!\\5)\\s+)?((\\6))$",
            "error": "Compilation failed: reference to non-existent subpattern at offset 6"
        },
        {
            "pattern": "^((?!\\5)\\s+)?((\\6))$",
            "error": "Compilation failed: reference to non-existent subpattern at offset 6"
        },
        {
            "pattern": "^((?!\\5)\\s+)?((\\6))$",
            "error": "Compilation failed: reference to non-existent subpattern at offset 6"
        },
        {
            "pattern": "^((?!\\5)\\s+)?((\\6))$",
            "error": "Compilation failed: reference to non-existent subpattern at offset 6"
        },
        {
            "pattern": "^((?!\\5)\\s+)?((\\6))$",
            "error": "Compilation failed: reference to non-existent subpattern at offset 6"
        },
        {
            "pattern": "^((?!\\5)\\s+)?((\\6))$",
            "error": "Compilation failed: reference to non-existent subpattern at offset 6"
        },
        {
            "pattern": "^((?!\\5)\\s+)?((\\6))$",
            "error": "Compilation failed: reference to non-existent subpattern at offset 6"
        },
        {
            "pattern": "^((?!\\5)\\s+)?((\\6))$",
            "error": "Compilation failed: reference to non-existent subpattern at offset 6"
        },
        {
            "pattern": "^((?!\\5)\\s+)?((\\6))$",
            "error": "Compilation failed: reference to non-existent subpattern at offset 6"
        },
        {
            "pattern": "^((?!\\5)\\s+)?((\\6))$",
            "error": "Compilation failed: reference to non-existent subpattern at offset 6"
        },
        {
            "pattern": "^((?!\\5)\\s+)?((\\6))$",
            "error": "Compilation failed: reference to non-existent subpattern at offset 6"
        },
        {
            "pattern": "^((?!\\5)\\s+)?((\\6))$",
            "error": "Compilation failed: reference to non-existent subpattern at offset 6"
        },
        {
            "pattern": "^((?!\\5)\\s+)?((\\6))$",
            "error": "Compilation failed: reference to non-existent subpattern at offset 6"
        },
        {
            "pattern": "^((?!\\5)\\s+)?((\\6))$",
            "error": "Compilation failed: reference to non-existent subpattern at offset 6"
        },
        {
            "pattern": "^((?!\\5)\\s+)?((\\6))$",
            "error": "Compilation failed: reference to non-existent subpattern at offset 6"
        },
        {
            "pattern": "^((?!\\5)\\s+)?((\\6))$",
            "error": "Compilation failed: reference to non-existent subpattern at offset 6"
        },
        {
            "pattern": "(\\$)[!#$%()*,-/:-@\\[-_ab|~](?![0-9A-Z_a-z])",
            "error": "Unknown modifier ':'"
        }
    ]
}